webdriver_bot/__init__.py
webdriver_bot/bot.py
webdriver_bot/webdrivers/__init__.py
webdriver_bot/webdrivers/chromedriver.exe
webdriver_bot/webdrivers/chromedriverLinux
webdriver_bot/webdrivers/user_agents.csv
webdriver_bot-0.33.dist-info/METADATA
webdriver_bot-0.33.dist-info/WHEEL
webdriver_bot-0.33.dist-info/top_level.txt
webdriver_bot-0.33.dist-info/RECORD
