Metadata-Version: 2.1
Name: webdriver-bot
Version: 0.33
Summary: wrapper for selenium
Home-page: https://github.com/zbagdzevicius/webdriver_bot
Author: Zygimantas Bagdzevicius
Author-email: zbagdzevicius@gmail.com
License: UNKNOWN
Platform: UNKNOWN
Classifier: Programming Language :: Python :: 3
Classifier: License :: OSI Approved :: MIT License
Classifier: Operating System :: OS Independent
Requires-Dist: selenium
